mysqler/__init__.py
mysqler/mysql.py
mysqler/py.typed
mysqler/table.py
mysqler-0.1.0.dist-info/LICENSE
mysqler-0.1.0.dist-info/WHEEL
mysqler-0.1.0.dist-info/METADATA
mysqler-0.1.0.dist-info/RECORD
